lastfm/__init__.py
lastfm/client.py
lastfm/errors.py
lastfm_py-0.0.1.dist-info/LICENSE
lastfm_py-0.0.1.dist-info/METADATA
lastfm_py-0.0.1.dist-info/WHEEL
lastfm_py-0.0.1.dist-info/top_level.txt
lastfm_py-0.0.1.dist-info/RECORD
