Metadata-Version: 2.1
Name: lastfm-py
Version: 0.0.1
Summary: An asynchronous LastFM API wrapper
Home-page: https://github.com/twitch0001/lastfm-py
Author: twitch7443
Author-email: twitch7443@pm.me
License: UNKNOWN
Platform: UNKNOWN
Classifier: Programming Language :: Python :: 3
Classifier: License :: OSI Approved :: MIT License
